vcfxplr/__init__.py
vcfxplr/py.typed
vcfxplr/scripts/main.py
vcfxplr-0.1.2.dist-info/entry_points.txt
vcfxplr-0.1.2.dist-info/LICENSE.md
vcfxplr-0.1.2.dist-info/WHEEL
vcfxplr-0.1.2.dist-info/METADATA
vcfxplr-0.1.2.dist-info/RECORD
