Metadata-Version: 2.1
Name: vcfxplr
Version: 0.1.2
Summary: CLI tool to explore and export data from a VCF / vCard file
Home-page: https://github.com/bergercookie/vcfxplr
License: MIT
Author: Nikos Koukis
Author-email: nickkouk@gmail.com
Requires-Python: >=3.8,<4.0
Classifier: Framework :: Pytest
Classifier: License :: OSI Approved :: MIT License
Classifier: Natural Language :: English
Classifier: Operating System :: Unix
Classifier: Programming Language :: Python
Classifier: Programming Language :: Python :: 3
Classifier: Programming Language :: Python :: 3 :: Only
Classifier: Programming Language :: Python :: 3.10
Classifier: Programming Language :: Python :: 3.8
Classifier: Programming Language :: Python :: 3.9
Classifier: Topic :: Utilities
Requires-Dist: bubop (>=0.1.6,<0.2.0)
Requires-Dist: vobject (>=0.9.6,<0.10.0)
Project-URL: Repository, https://github.com/bergercookie/vcfxplr
